{
	"info": {
		"_postman_id": "22cd1052-9ec7-47ec-a2d6-6f36b275aa47",
		"name": "weather-forecasts",
		"schema": "https://schema.getpostman.com/json/collection/v2.1.0/collection.json"
	},
	"item": [
		{
			"name": "get_weather_city_long_lat",
			"request": {
				"method": "GET",
				"header": [],
				"url": {
					"raw": "https://localhost:5001/WeatherForecastOpen",
					"protocol": "https",
					"host": [
						"localhost"
					],
					"port": "5001",
					"path": [
						"WeatherForecastOpen"
					]
				}
			},
			"response": []
		},
		{
			"name": "get_weather_city_only",
			"request": {
				"method": "GET",
				"header": [],
				"url": null
			},
			"response": []
		}
	]
}